lium_diarization_editor/__init__.py
lium_diarization_editor/cli.py
lium_diarization_editor/diarization.py
lium_diarization_editor/lium.py
lium_diarization_editor-0.1.1.dist-info/METADATA
lium_diarization_editor-0.1.1.dist-info/WHEEL
lium_diarization_editor-0.1.1.dist-info/entry_points.txt
lium_diarization_editor-0.1.1.dist-info/top_level.txt
lium_diarization_editor-0.1.1.dist-info/RECORD
