Metadata-Version: 2.1
Name: lium-diarization-editor
Version: 0.1.1
Summary: Editor/viewer for LIUM diarizations.
Home-page: https://github.com/maxhollmann/lium-diarization-editor
Author: Max Hollmann
Author-email: maxhollmann@gmail.com
License: MIT
Platform: UNKNOWN
Requires-Python: >=3.6.0
Requires-Dist: python-mpv
Requires-Dist: matplotlib
Requires-Dist: click
Requires-Dist: pandas
